llama_toolchain/__init__.py
llama_toolchain/utils.py
llama_toolchain/cli/__init__.py
llama_toolchain/cli/download.py
llama_toolchain/cli/llama.py
llama_toolchain/cli/subcommand.py
llama_toolchain/cli/table.py
llama_toolchain/cli/inference/__init__.py
llama_toolchain/cli/inference/configure.py
llama_toolchain/cli/inference/inference.py
llama_toolchain/cli/inference/start.py
llama_toolchain/cli/model/__init__.py
llama_toolchain/cli/model/describe.py
llama_toolchain/cli/model/list.py
llama_toolchain/cli/model/model.py
llama_toolchain/cli/model/template.py
llama_toolchain/common/__init__.py
llama_toolchain/common/deployment_types.py
llama_toolchain/common/training_types.py
llama_toolchain/data/default_inference_config.yaml
llama_toolchain/inference/__init__.py
llama_toolchain/inference/api_instance.py
llama_toolchain/inference/client.py
llama_toolchain/inference/event_logger.py
llama_toolchain/inference/generation.py
llama_toolchain/inference/inference.py
llama_toolchain/inference/model_parallel.py
llama_toolchain/inference/parallel_utils.py
llama_toolchain/inference/server.py
llama_toolchain/inference/api/__init__.py
llama_toolchain/inference/api/config.py
llama_toolchain/inference/api/datatypes.py
llama_toolchain/inference/api/endpoints.py
llama_toolchain/memory/__init__.py
llama_toolchain/memory/api/__init__.py
llama_toolchain/memory/api/datatypes.py
llama_toolchain/memory/api/endpoints.py
llama_toolchain/safety/__init__.py
llama_toolchain/safety/api/__init__.py
llama_toolchain/safety/api/config.py
llama_toolchain/safety/api/datatypes.py
llama_toolchain/safety/shields/__init__.py
llama_toolchain/safety/shields/base.py
llama_toolchain/safety/shields/code_scanner.py
llama_toolchain/safety/shields/llama_guard.py
llama_toolchain/safety/shields/prompt_guard.py
llama_toolchain/safety/shields/shield_runner.py
llama_toolchain/safety/shields/contrib/__init__.py
llama_toolchain/safety/shields/contrib/third_party_shield.py
llama_cmdline-0.0.1rc1.dist-info/LICENSE
llama_cmdline-0.0.1rc1.dist-info/METADATA
llama_cmdline-0.0.1rc1.dist-info/WHEEL
llama_cmdline-0.0.1rc1.dist-info/entry_points.txt
llama_cmdline-0.0.1rc1.dist-info/top_level.txt
llama_cmdline-0.0.1rc1.dist-info/RECORD
