Metadata-Version: 2.1
Name: llama-cmdline
Version: 0.0.1rc1
Summary: Llama CLI
Home-page: https://github.com/meta-llama/llama-toolchain
Author: Meta Llama
Author-email: llama-oss@meta.com
Requires-Python: >=3.10
License-File: LICENSE
Requires-Dist: accelerate
Requires-Dist: black ==24.4.2
Requires-Dist: blobfile
Requires-Dist: codeshield
Requires-Dist: fairscale
Requires-Dist: fastapi
Requires-Dist: fire
Requires-Dist: flake8
Requires-Dist: httpx
Requires-Dist: huggingface-hub
Requires-Dist: hydra-core
Requires-Dist: hydra-zen
Requires-Dist: json-strong-typing
Requires-Dist: llama-models
Requires-Dist: matplotlib
Requires-Dist: omegaconf
Requires-Dist: pandas
Requires-Dist: Pillow
Requires-Dist: pre-commit
Requires-Dist: pydantic ==1.10.13
Requires-Dist: pydantic-core ==2.18.2
Requires-Dist: python-dotenv
Requires-Dist: python-openapi
Requires-Dist: requests
Requires-Dist: tiktoken
Requires-Dist: torch
Requires-Dist: transformers
Requires-Dist: ufmt ==2.7.0
Requires-Dist: usort ==1.0.8
Requires-Dist: uvicorn
Requires-Dist: zmq
